secsgml/__init__.py
secsgml/header_standardization.py
secsgml/parse_sgml.py
secsgml/utils.py
secsgml/write_sgml.py
secsgml-0.3.5.dist-info/METADATA
secsgml-0.3.5.dist-info/WHEEL
secsgml-0.3.5.dist-info/top_level.txt
secsgml-0.3.5.dist-info/RECORD
