Metadata-Version: 2.4
Name: secsgml
Version: 0.3.5
Summary: Parse Securities and Exchange Commission Standard Generalized Markup Language (SEC SGML) files
Author: John Friedman
Author-email: johnfriedman@datamule.xyz
License: MIT
Requires-Python: >=3.6
Dynamic: author
Dynamic: author-email
Dynamic: license
Dynamic: requires-python
Dynamic: summary
